{
  "name": "University",
  "_id": "fb3pOkKJqew81G3f",
  "pages": [
    {
      "sort": 100000,
      "name": "Description",
      "type": "text",
      "_id": "K4H4dhO7wRVZWPJB",
      "system": {},
      "title": {
        "show": true,
        "level": 1
      },
      "image": {},
      "text": {
        "format": 1,
        "content": "<p>This settlement is built on what was once a university campus. The libraries may still be stocked and untouched. The traditions of the university may have taken on a strange or religious form. Class may still be in session.</p>"
      },
      "video": {
        "controls": true,
        "volume": 0.5
      },
      "src": null,
      "category": null,
      "_key": "!journal.pages!fb3pOkKJqew81G3f.K4H4dhO7wRVZWPJB"
    }
  ],
  "folder": null,
  "categories": [],
  "sort": 0,
  "_key": "!journal!fb3pOkKJqew81G3f"
}
